exif_sorter/__init__.py
exif_sorter/cli.py
exif_sorter/py.typed
exif_sorter/sorter.py
exif_sorter/utils/__init__.py
exif_sorter/utils/dsstore.py
exif_sorter/utils/duplicates.py
exif_sorter/utils/exif.py
exif_sorter-1.1.0.dist-info/licenses/LICENSE
exif_sorter-1.1.0.dist-info/METADATA
exif_sorter-1.1.0.dist-info/WHEEL
exif_sorter-1.1.0.dist-info/entry_points.txt
exif_sorter-1.1.0.dist-info/top_level.txt
exif_sorter-1.1.0.dist-info/RECORD
