Metadata-Version: 2.4
Name: exif-sorter
Version: 1.1.0
Summary: Organize photos, videos, and audio files by EXIF/ID3 creation date
Author-email: "David A. Macey" <davidamacey@gmail.com>
License-Expression: MIT
Project-URL: Homepage, https://github.com/davidamacey/exif-sorter
Project-URL: Documentation, https://github.com/davidamacey/exif-sorter#readme
Project-URL: Repository, https://github.com/davidamacey/exif-sorter
Project-URL: Changelog, https://github.com/davidamacey/exif-sorter/blob/main/CHANGELOG.md
Project-URL: Issues, https://github.com/davidamacey/exif-sorter/issues
Keywords: exif,photos,organize,media,sort,videos,images,audio,id3,quicktime,docker,exiftool
Classifier: Development Status :: 4 - Beta
Classifier: Environment :: Console
Classifier: Intended Audience :: End Users/Desktop
Classifier: Operating System :: OS Independent
Classifier: Programming Language :: Python :: 3
Classifier: Programming Language :: Python :: 3.11
Classifier: Programming Language :: Python :: 3.12
Classifier: Programming Language :: Python :: 3.13
Classifier: Topic :: Multimedia :: Graphics
Classifier: Topic :: System :: Filesystems
Classifier: Typing :: Typed
Requires-Python: >=3.11
License-File: LICENSE
Requires-Dist: PyExifTool<1.0,>=0.5.6
Requires-Dist: imohash<2.0,>=1.1.0
Requires-Dist: tqdm<5.0,>=4.66.0
Provides-Extra: dev
Requires-Dist: build>=1.0.0; extra == "dev"
Requires-Dist: ipykernel>=6.0; extra == "dev"
Requires-Dist: jupyter>=1.0; extra == "dev"
Requires-Dist: mypy>=1.0; extra == "dev"
Requires-Dist: pytest>=7.0; extra == "dev"
Requires-Dist: pytest-cov>=4.0; extra == "dev"
Requires-Dist: ruff>=0.8.0; extra == "dev"
Dynamic: license-file
